{
  "id": "tnfpwdokva",
  "destination": "マサイマラ国立保護区（ケニア）",
  "description": "家族でケニアのマサイマラを訪れ、広大なサバンナで「ビッグファイブ」を探索する贅沢なサファリ旅行プランです。子供の安全と快適性を最優先し、国内線移動と高級ロッジ滞在で、ゆったりとしたペースで本物の野生動物との出会いを実現します。サファリカーに乗り、本物のライオンを観察する冒険に焦点を当てます。",
  "days": [
    {
      "day": 1,
      "title": "日本出発・長距離移動",
      "activities": [
        {
          "time": "午前",
          "activity": "自宅から日本の国際空港へ移動",
          "description": "家族旅行（子供連れ）のため、余裕を持って日本の国際空港（成田または羽田など）へ移動します。チェックイン前に子供がリラックスできる時間を作ります。"
        },
        {
          "time": "昼食",
          "activity": "空港内のレストランで昼食",
          "description": "長時間のフライトに備え、食べ慣れた和食や子供が好きなメニューを選び、リラックスして昼食をとります。"
        },
        {
          "time": "午後",
          "activity": "チェックイン、出国手続き、ラウンジで休憩",
          "description": "予算が高めのため、ビジネスクラスまたはプレミアムエコノミーを利用し、スムーズにチェックイン。空港ラウンジでフライトまでの時間をゆったり過ごします。"
        },
        {
          "time": "夕食",
          "activity": "機内食（1回目）",
          "description": "ヨーロッパまたは中東主要都市を経由する長距離フライトに搭乗。子供向けの特別食を事前に手配し、機内食を楽しみます。"
        },
        {
          "time": "夜",
          "activity": "機内泊",
          "description": "長時間のフライト。家族全員が快適に休めるよう、座席選びや機内エンターテイメントを活用しつつ、翌日のケニア到着に備えて休息をとります。"
        }
      ]
    },
    {
      "day": 2,
      "title": "ナイロビ経由、マサイマラ到着とショートサファリ",
      "activities": [
        {
          "time": "早朝",
          "activity": "機内食（2回目）とナイロビ到着準備",
          "description": "経由地からナイロビへ向かうフライトで朝食をとり、ケニア入国に備えます。時差ボケ対策のため、機内で水分補給を心がけます。"
        },
        {
          "time": "午前",
          "activity": "ジョモ・ケニヤッタ国際空港 (NBO) 到着・入国審査",
          "description": "ナイロビのNBOに到着後、入国審査を済ませます。現地ガイドと合流し、国内線用のウィルソン空港 (WIL) へ専用車で移動します。"
        },
        {
          "time": "昼食",
          "activity": "ウィルソン空港 (WIL) 付近で軽食",
          "description": "国内線への乗り継ぎ時間を利用し、WILのラウンジなどで軽めのランチを済ませます。マサイマラ行きの小型機に搭乗する準備をします。"
        },
        {
          "time": "午後",
          "activity": "マサイマラへ小型機で移動、ロッジ到着",
          "description": "ウィルソン空港からマサイマラ行きの小型機（ブッシュプレーン）に搭乗（約1時間）。着陸後、ロッジのサファリカーに乗り換え、高級テントキャンプ/ロッジへ移動し、チェックインします。"
        },
        {
          "time": "夕食",
          "activity": "ロッジでの優雅なディナー",
          "description": "マサイマラ到着を祝し、豪華な設備を備えたロッジのダイニングエリアで洗練されたディナーを楽しみます。子供の好みに合わせたメニューも提供されます。"
        },
        {
          "time": "夜",
          "activity": "ショートサファリ（サンセットゲームドライブ）",
          "description": "子供の「サファリカーに乗りたい」という要望に応え、疲れすぎないよう短時間（約1.5時間）のゲームドライブに出発。夕焼けの中、サバンナの動物たちとの初めての出会いを楽しみます。"
        }
      ]
    },
    {
      "day": 3,
      "title": "ライオン探索とビッグファイブの追跡",
      "activities": [
        {
          "time": "06:00",
          "activity": "マサイマラ国立保護区（早朝ゲームドライブ）",
          "description": "子供が本物のライオンを見るチャンスを最大化するため、早朝の涼しい時間帯に出発。ガイドと共にライオンのテリトリーへ向かい、新鮮な足跡を追跡する冒険的なドライブを楽しむ。"
        },
        {
          "time": "08:30",
          "activity": "朝食（ブッシュブレックファスト）",
          "description": "サバンナの安全な場所で、温かいブッシュブレックファストを楽しむ。新鮮な空気の中で食べる朝食は格別。子供が好きなメニューも用意し、リラックスした時間を過ごす。"
        },
        {
          "time": "10:00",
          "activity": "サバンナのライオンテリトリー探索",
          "description": "ライオンの休息時間に入る前に、テリトリー周辺をゆっくりと巡る。ビッグファイブの他の動物（ゾウ、バッファローなど）も探し、子供の好奇心を刺激する。"
        },
        {
          "time": "12:30",
          "activity": "昼食（ロッジ/キャンプ）",
          "description": "午後の暑さを避けるため、ロッジに戻り、快適な環境で昼食。子供が休憩できるよう、午後のアクティビティ開始まで十分な休息時間を確保する。"
        },
        {
          "time": "15:30",
          "activity": "午後のゲームドライブ（水飲み場へ）",
          "description": "暑さが和らぎ、動物たちが水を求めて集まる時間帯を狙い、水飲み場へ移動。カバやキリン、様々な種類のシカなど、多様な動物の生態を観察する。"
        },
        {
          "time": "18:30",
          "activity": "サンセット鑑賞とロッジへ帰還",
          "description": "サバンナに沈む壮大な夕日を鑑賞。子供と一緒に今日の発見や感動を共有しながら、ゆっくりとロッジへ戻る。"
        },
        {
          "time": "19:30",
          "activity": "夕食（ロッジ/キャンプ）",
          "description": "ロッジのレストランで、家族で楽しめるメニューをゆっくりと味わう。早朝からの活動で疲れた体を休める。"
        }
      ]
    },
    {
      "day": 4,
      "title": "終日サファリとマラ川の絶景",
      "activities": [
        {
          "time": "07:00",
          "activity": "朝食（ロッジ）",
          "description": "終日サファリに備え、ロッジでしっかりと朝食を摂る。ランチボックスと十分な飲み物を準備し、出発に備える。"
        },
        {
          "time": "08:00",
          "activity": "広大な平原（ヌーやシマウマの群れ）への移動",
          "description": "マラ川方面へ向かうため、広大な平原を横断。大移動の時期であれば、数えきれないほどのヌーやシマウマの群れを観察し、自然の壮大さを体感する。"
        },
        {
          "time": "10:30",
          "activity": "マラ川（カバ、ワニの観察）",
          "description": "マラ川に到着。川岸に潜む巨大なナイルワニや、水中で群れるカバの様子を安全な場所から観察する。大移動の時期であれば、川渡りの痕跡を探す。"
        },
        {
          "time": "12:30",
          "activity": "昼食（ブッシュランチスポット）",
          "description": "景色が良く、安全が確保されたブッシュランチスポットでピクニックランチ。自然の中で食べる特別なランチは、子供にとって最高の冒険体験となる。"
        },
        {
          "time": "14:00",
          "activity": "マラ川周辺の探索と休憩",
          "description": "川周辺の生態系を観察しつつ、サファリカー内で休憩を取りながらゆっくりと移動。子供のペースに合わせ、疲労を感じさせないよう配慮する。"
        },
        {
          "time": "16:00",
          "activity": "平原を横断しながらロッジへ帰還",
          "description": "帰路は、夕方の光の中で活動を始めるチーターやヒョウなどの捕食動物を探しながら、広大な平原をゆっくりと横断する。"
        },
        {
          "time": "19:30",
          "activity": "夕食（特別なディナー）",
          "description": "終日サファリの成功を祝い、ロッジで提供される特別なディナー（例：ボマディナーなど）を楽しむ。家族の思い出に残る豪華な食事を提供する。"
        }
      ]
    },
    {
      "day": 5,
      "title": "マサイ文化体験と夕暮れのサファリ",
      "activities": [
        {
          "time": "07:00",
          "activity": "朝食",
          "description": "宿泊ロッジ/テントキャンプにて、豪華なビュッフェ形式の朝食。子供が好きなメニューも豊富に用意されています。"
        },
        {
          "time": "08:30",
          "activity": "マサイ族の村（文化交流）訪問",
          "description": "サファリカーで近くの**マサイ族の村**へ移動。伝統的な歓迎の歌と踊り（ジャンプダンス）を体験し、彼らの生活様式（火起こしや家屋の見学）を学びます。子供たちにとって貴重な異文化交流の機会となります。"
        },
        {
          "time": "11:00",
          "activity": "ロッジに戻り休憩",
          "description": "午前中の活動で疲れた体を休めるため、ロッジのプールサイドやテラスでリラックスタイム。ゆっくりとしたペースで過ごします。"
        },
        {
          "time": "13:00",
          "activity": "昼食",
          "description": "ロッジにて優雅なランチ。ケニアの新鮮な食材を使った料理を楽しみます。"
        },
        {
          "time": "15:30",
          "activity": "イブニング・ゲームドライブ開始",
          "description": "午後のゲームドライブへ出発。特に**チーターの生息地**として知られる開けた平原を重点的に巡り、チーターやヒョウなどのネコ科動物の狩りの様子を探します。"
        },
        {
          "time": "17:30",
          "activity": "サンセット鑑賞（サンダウナー）",
          "description": "**保護区内の見晴らしの良い丘**へ移動。サファリカーを停め、マサイマラの壮大な夕日を鑑賞します。ロッジが用意した軽食と飲み物（サンダウナー）を楽しみながら、絶景を堪能します。"
        },
        {
          "time": "20:00",
          "activity": "夕食",
          "description": "ロッジのレストランで、洗練されたコースディナー。家族で一日の冒険や発見を語り合います。"
        }
      ]
    },
    {
      "day": 6,
      "title": "最後のサファリとナイロビへの移動",
      "activities": [
        {
          "time": "06:30",
          "activity": "モーニング・ゲームドライブ（最終日）",
          "description": "早朝の動物の活動が最も活発な時間帯を狙って、最後のゲームドライブへ。特に子供が見たがっているライオンなど、見逃している動物を重点的に探します。"
        },
        {
          "time": "08:30",
          "activity": "ロッジに戻り朝食",
          "description": "ロッジに戻り、たっぷりと朝食をいただきます。チェックアウトの準備も並行して行います。"
        },
        {
          "time": "10:00",
          "activity": "チェックアウトと移動",
          "description": "ロッジをチェックアウトし、専用サファリカーで**マサイマラの滑走路**（Airstrip）へ移動。道中も最後のサファリを楽しみます。"
        },
        {
          "time": "12:00",
          "activity": "マサイマラ発（小型飛行機）",
          "description": "小型飛行機に搭乗し、ナイロビのウィルソン空港へ向かいます。上空からマサイマラの広大な景色を眼下に収めます。"
        },
        {
          "time": "13:30",
          "activity": "ナイロビ到着＆移動",
          "description": "ナイロビ到着後、専用車で市内へ移動します。"
        },
        {
          "time": "14:30",
          "activity": "昼食",
          "description": "ナイロビ市内の洗練されたレストランで、軽めのランチ。サファリとは異なる都会の雰囲気を楽しみます。"
        },
        {
          "time": "16:00",
          "activity": "**ナイロビ市内の高級ホテル**にチェックイン",
          "description": "治安と快適性を重視した高級ホテルにチェックイン。長旅の疲れを癒すため、少し休憩を取ります。"
        },
        {
          "time": "19:30",
          "activity": "夕食（ケニア料理レストラン）",
          "description": "ナイロビで有名な**ケニア料理レストラン**へ移動。肉料理を中心としたケニアの伝統的なグリル料理を体験し、サファリの成功を祝います。"
        }
      ]
    },
    {
      "day": 7,
      "title": "子供向け動物施設訪問と帰国準備",
      "activities": [
        {
          "time": "07:30",
          "activity": "朝食",
          "description": "ナイロビ市内の宿泊施設にて、ゆっくりと最後の朝食を楽しみます。"
        },
        {
          "time": "09:00",
          "activity": "チェックアウトと移動",
          "description": "ホテルをチェックアウトし、荷物を預け、午前中のアクティビティへ向かいます。帰国便に備え、移動しやすいように準備します。"
        },
        {
          "time": "10:30",
          "activity": "デイビッド・シェルドリック野生動物トラスト訪問",
          "description": "（象の孤児院）一般公開時間に合わせて訪問。子供たちが間近で子象のミルクタイムを見学できる、感動的な体験です。サファリとはまた違った、保護活動の側面を学びます。"
        },
        {
          "time": "12:30",
          "activity": "昼食",
          "description": "カレン・ブリクセン博物館周辺の落ち着いたカフェやレストランで昼食。家族でリラックスできる空間を選びます。"
        },
        {
          "time": "14:00",
          "activity": "カレン・ブリクセン博物館周辺散策",
          "description": "映画『愛と哀しみの果て』の舞台となった美しいエリアを散策。時間があれば博物館を軽く見学し、ケニアの歴史と文化に触れます。"
        },
        {
          "time": "16:00",
          "activity": "ジョモ・ケニヤッタ国際空港 (NBO) へ移動",
          "description": "帰国便に備え、早めに空港へ向かいます。ナイロビ市内の交通状況を考慮し、余裕をもって移動を開始します。"
        },
        {
          "time": "17:30",
          "activity": "チェックイン手続き",
          "description": "国際線（日本行き）のチェックイン手続きを行います。長距離フライトに備え、座席や荷物の確認をします。"
        },
        {
          "time": "19:00",
          "activity": "夕食",
          "description": "空港ラウンジまたは搭乗ゲート近くのレストランで、軽めの夕食を済ませます。"
        },
        {
          "time": "21:00",
          "activity": "日本へ向けて出発",
          "description": "ジョモ・ケニヤッタ国際空港より、乗り継ぎ便にて日本へ向けて出発します。"
        }
      ]
    },
    {
      "day": 8,
      "title": "日本到着",
      "activities": [
        {
          "time": "終日",
          "activity": "帰路（機内泊・乗り継ぎ）",
          "description": "ケニアからの長距離フライト（乗り継ぎを含む）で終日を過ごします。機内では家族でゆっくりと休息を取り、サファリの思い出を語り合います。"
        },
        {
          "time": "午後",
          "activity": "乗り継ぎ空港での休憩",
          "description": "乗り継ぎ空港（中東やヨーロッパの主要ハブ空港など）にて休憩。子供の気分転換のため、空港内の施設やキッズスペースを利用し、リフレッシュします。"
        },
        {
          "time": "夜 (または翌日早朝)",
          "activity": "日本到着",
          "description": "日本の主要国際空港に到着。入国審査、荷物受け取り後、帰宅。長旅の疲れを癒し、ケニアでの素晴らしい冒険の記憶を大切にします。"
        }
      ]
    }
  ],
  "references": [
    {
      "title": "Blog Post",
      "url": "https://travel.tomokichidiary.com/posts/spain7",
      "snippet": "フカレーとハヤシライスの間みたいな感じ、私的には好みドンピシャでとても美味しかったです。\r\nベルギービールは、実は私、ビールがあまり得意ではなく、日本では飲めなかったのですが、せっかくベルギーに来てビールを飲まないのもなと思い、注文してみました。\r\nいくつか種類があり、店員さんにお願いして飲みやすいものにしてもらったのですが、とても飲みやすく、ビールが苦手な私でも美味しく飲むことができました。\r\n..."
    }
  ]
}