{
  "id": "jd6or2fk51",
  "destination": "ニューヨーク",
  "description": "4泊6日でニューヨークの主要な観光地、世界的な美術館、そして本場のエンターテイメント（ブロードウェイミュージカル、ジャズ）をアクティブに巡る、充実した都市観光プランです。マンハッタンを中心に、ブルックリンまで足を延ばし、ニューヨークの多様な魅力を体験します。",
  "heroImage": "https://images.unsplash.com/photo-1568515387631-8b650bbcdb90?crop=entropy&cs=tinysrgb&fit=max&fm=jpg&ixid=M3w4NTQ4NTd8MHwxfHJhbmRvbXx8fHx8fHx8fDE3NjgzOTUzMTF8&ixlib=rb-4.1.0&q=80&w=1080",
  "heroImagePhotographer": "Jermaine Ee",
  "heroImagePhotographerUrl": "https://unsplash.com/@eejermaine?utm_source=Tabidea&utm_medium=referral",
  "days": [
    {
      "day": 1,
      "title": "日本出発・ニューヨーク到着",
      "activities": [
        {
          "time": "午前",
          "activity": "日本出発",
          "description": "成田または羽田からニューヨークへ向けて出発。長時間のフライトとなるため、機内ではリラックスして過ごし、時差ボケ対策に努める。"
        },
        {
          "time": "15:00頃",
          "activity": "ジョン・F・ケネディ国際空港 (JFK) またはニューアーク・リバティー国際空港 (EWR) 到着",
          "description": "入国審査後、マンハッタンへ移動。予算が高めのため、タクシーまたは快適な定額シャトルサービスを利用し、スムーズにホテルへ向かう。"
        },
        {
          "time": "17:00",
          "activity": "ホテルチェックイン",
          "description": "ミッドタウン周辺など、観光に便利なエリアのホテルにチェックイン。荷物を整理し、長旅の疲れを軽く癒す。"
        },
        {
          "time": "19:00",
          "activity": "夕食（ニューヨーク初日のグルメ体験）",
          "description": "ホテル周辺の評判の高いステーキハウスやモダンアメリカンレストランで、ニューヨーク到着を祝う豪華な夕食を楽しむ。"
        },
        {
          "time": "21:00",
          "activity": "街の散策と準備",
          "description": "ホテル周辺を軽く散策し、ニューヨークの夜の雰囲気を味わう。翌日のアクティブな行動に備え、早めに就寝する。"
        }
      ]
    },
    {
      "day": 2,
      "title": "ミッドタウンの象徴とブロードウェイ体験",
      "activities": [
        {
          "time": "8:00",
          "activity": "朝食（ニューヨークスタイル）",
          "description": "ホテル近くのデリやカフェで、ベーグルやエッグサンドイッチなど、ニューヨークらしい朝食を楽しむ。"
        },
        {
          "time": "9:30",
          "activity": "ロックフェラー・センター観光",
          "description": "ミッドタウンの象徴であるロックフェラー・センターへ。展望台「トップ・オブ・ザ・ロック」に登り、午前中のクリアな空気の中で壮大なパノラマビューを満喫する。"
        },
        {
          "time": "11:30",
          "activity": "5番街（ショッピング）",
          "description": "ロックフェラー・センターから南下し、世界有数の高級ブランド店が並ぶ5番街を散策。ウィンドウショッピングを楽しみつつ、予算に合わせて気になる店舗で買い物を楽しむ。"
        },
        {
          "time": "13:30",
          "activity": "昼食（グルメ）",
          "description": "5番街周辺の洗練されたレストランや、高級フードコートで質の高いランチを取る。午後の活動に備えてエネルギーをチャージ。"
        },
        {
          "time": "15:00",
          "activity": "タイムズスクエア散策",
          "description": "「世界の交差点」タイムズスクエアへ移動。昼間でも圧倒的なネオンと広告、そして人々の熱気を体感し、ニューヨークのエネルギーを感じる。"
        },
        {
          "time": "18:30",
          "activity": "夕食（ブロードウェイ前のグルメ）",
          "description": "ブロードウェイの開演時間に間に合うよう、劇場街周辺の人気のビストロやレストランで早めの夕食を取る。予約推奨。"
        },
        {
          "time": "20:00",
          "activity": "ブロードウェイ（ミュージカル鑑賞）",
          "description": "楽しみにしていた本場のブロードウェイミュージカルを鑑賞。事前に人気の演目の良い席を確保し、ニューヨーク最大のエンターテイメントを満喫する。"
        }
      ]
    },
    {
      "day": 3,
      "title": "世界的なアートとセントラルパーク",
      "activities": [
        {
          "time": "08:00",
          "activity": "朝食（アッパーイーストサイド）",
          "description": "ホテル周辺、またはアッパーイーストサイドの高級デリやカフェで、ニューヨークらしいベーグルやエッグサンドイッチを優雅に楽しむ。"
        },
        {
          "time": "09:30",
          "activity": "メトロポリタン美術館 (MET) 鑑賞",
          "description": "開館と同時に入場し、混雑を避けてじっくり鑑賞。世界最大級のコレクションの中から、特にエジプト美術やヨーロッパ絵画、屋上庭園からの景色を楽しむ。"
        },
        {
          "time": "12:30",
          "activity": "昼食（アッパーイーストサイド）",
          "description": "MET周辺の洗練されたレストランでランチ。または、MET内のPetrie Court Cafeなどで優雅に軽食を摂り、午後の活動に備える。"
        },
        {
          "time": "14:00",
          "activity": "セントラルパーク散策",
          "description": "METから徒歩でセントラルパークへ。ベセスダ・テラス、ストロベリー・フィールズ、ザ・モールなど、都会のオアシスをアクティブに散策し、リフレッシュする。"
        },
        {
          "time": "17:00",
          "activity": "MoMA (近代美術館) 鑑賞",
          "description": "ミッドタウンへ移動し、MoMAへ。ゴッホの「星月夜」やピカソ、ウォーホルなど、近代・現代アートの傑作を鑑賞する。閉館時間近くまで利用し、比較的空いている時間帯を狙う。"
        },
        {
          "time": "19:30",
          "activity": "グランド・セントラル・ターミナル見学",
          "description": "MoMAから徒歩圏内。歴史的な建築美を誇るターミナルを見学。メインコンコースの天井画や、情報ブースの時計など、細部まで鑑賞する。"
        },
        {
          "time": "20:30",
          "activity": "夕食（ミッドタウン・高級ディナー）",
          "description": "ミッドタウン周辺の高級ステーキハウスや、評価の高いフレンチレストランで、予算高めの贅沢なディナーを楽しむ。"
        }
      ]
    },
    {
      "day": 4,
      "title": "ダウンタウンの歴史とトレンド散策",
      "activities": [
        {
          "time": "08:00",
          "activity": "朝食",
          "description": "ホテル周辺でしっかりとした朝食を摂り、ダウンタウン散策に備える。"
        },
        {
          "time": "09:00",
          "activity": "ウォール街散策",
          "description": "地下鉄でロウアーマンハッタンへ移動。チャージング・ブル（雄牛の像）を見学し、ニューヨーク証券取引所など、金融街の活気ある雰囲気を体感する。"
        },
        {
          "time": "10:00",
          "activity": "9/11メモリアル＆ミュージアム訪問",
          "description": "9/11テロの犠牲者を追悼するメモリアルプールを見学後、ミュージアムで歴史を深く学ぶ。感情的な体験となるため、静かに時間をかけて見学する。"
        },
        {
          "time": "12:30",
          "activity": "昼食（フィナンシャル・ディストリクト）",
          "description": "ロウアーマンハッタン周辺で、質の高いシーフードやグルメバーガーなど、カジュアルながら満足度の高いランチを楽しむ。"
        },
        {
          "time": "14:00",
          "activity": "自由の女神像（スタテンアイランド・フェリー利用）",
          "description": "バッテリー・パークへ移動し、無料のスタテンアイランド・フェリーに乗船。船上から自由の女神像とマンハッタンのスカイラインを効率的に眺める。"
        },
        {
          "time": "16:30",
          "activity": "ソーホー (SOHO) / ノリータ (Nolita) 散策",
          "description": "ダウンタウンのトレンドエリアへ移動。ソーホーの鋳鉄建築とハイエンドなブティック、ノリータの個性的なショップやカフェを巡り、最新のトレンドをチェックしながら街歩きを楽しむ。"
        },
        {
          "time": "19:30",
          "activity": "夕食（ソーホー/ノリータ）",
          "description": "ソーホーまたはノリータのトレンディなレストランでディナー。話題のイタリアンやフュージョン料理など、グルメを楽しむ。"
        },
        {
          "time": "21:30",
          "activity": "ジャズクラブ体験（グリニッジ・ヴィレッジ）",
          "description": "グリニッジ・ヴィレッジの老舗ジャズクラブへ移動し、本場のライブパフォーマンスを堪能する。一人旅ならではの夜のエンターテイメントを満喫する。"
        }
      ]
    },
    {
      "day": 5,
      "title": "ブルックリンの風景とジャズナイト",
      "activities": [
        {
          "time": "8:00",
          "activity": "朝食（軽食）",
          "description": "ホテル周辺のデリやカフェで、コーヒーとベーグルなど、ニューヨーカーらしい軽めの朝食を摂り、アクティブな一日に備えます。"
        },
        {
          "time": "9:30",
          "activity": "ブルックリン・ブリッジ徒歩横断",
          "description": "マンハッタン側からブルックリン側へ、ブルックリン・ブリッジを徒歩で渡ります。朝の光の中で、マンハッタンの壮大なスカイラインを写真に収めます。"
        },
        {
          "time": "11:00",
          "activity": "ダンボ (DUMBO) 散策",
          "description": "橋を渡り終えた後、ダンボ地区へ。ウォーターフロントの公園（ブルックリン・ブリッジ・パーク）を散策し、有名なワシントン・ストリートからのフォトジェニックな景色を楽しみます。"
        },
        {
          "time": "12:30",
          "activity": "昼食（ウィリアムズバーグ）",
          "description": "地下鉄でウィリアムズバーグへ移動し、モダンでトレンディなレストランでランチ。地元の食材を活かした料理や、人気のグルメスポットを選びます。"
        },
        {
          "time": "14:00",
          "activity": "ウィリアムズバーグ散策とカフェ休憩",
          "description": "ベッドフォード・アベニュー周辺を中心に、おしゃれなブティックやヴィンテージショップ、インディペンデントなアートギャラリーを巡ります。途中で個性的なカフェに入り、休憩を兼ねて街の雰囲気を楽しみます。"
        },
        {
          "time": "17:00",
          "activity": "マンハッタンへ移動・休憩",
          "description": "地下鉄でマンハッタンに戻り、ホテルで少し休憩。夜のジャズクラブに向けて身支度を整えます。"
        },
        {
          "time": "18:30",
          "activity": "夕食（グリニッジ・ヴィレッジ周辺）",
          "description": "グリニッジ・ヴィレッジ周辺で、ジャズクラブの開場時間に合わせて早めの夕食。雰囲気の良いビストロやイタリアンで、落ち着いた食事を楽しみます。"
        },
        {
          "time": "20:30",
          "activity": "グリニッジ・ヴィレッジでジャズナイト",
          "description": "「Village Vanguard」や「Blue Note」など、歴史あるジャズクラブを訪れ、本場ニューヨークの熱いライブパフォーマンスを堪能します（チケットは事前予約推奨）。"
        }
      ]
    },
    {
      "day": 6,
      "title": "ニューヨーク出発・帰国へ",
      "activities": [
        {
          "time": "8:00",
          "activity": "朝食",
          "description": "ホテルまたは近隣のカフェで、最後のニューヨークの朝食をゆっくりと楽しみます。旅の思い出を振り返りながら、リラックスした時間を過ごします。"
        },
        {
          "time": "9:30",
          "activity": "最終ショッピングまたは散策",
          "description": "ホテル周辺で、お土産の買い足しや、まだ訪れていない近隣のエリアを軽く散策し、ニューヨークの街の雰囲気を最後まで味わいます。"
        },
        {
          "time": "11:00",
          "activity": "パッキングとチェックアウト準備",
          "description": "荷物を最終確認し、チェックアウトの準備をします。"
        },
        {
          "time": "12:00",
          "activity": "昼食（軽食）",
          "description": "空港への移動時間を考慮し、手早く済ませられる軽食やテイクアウトでランチを済ませます。"
        },
        {
          "time": "13:00",
          "activity": "ホテルチェックアウト",
          "description": "ホテルをチェックアウトします。フライト時間によっては、荷物を預けてさらに時間を有効活用することも可能です。"
        },
        {
          "time": "13:30",
          "activity": "空港へ移動開始",
          "description": "帰国便に合わせて、JFKまたはニューアーク空港へ移動を開始します。タクシー、シャトルバス、または公共交通機関を利用します。"
        },
        {
          "time": "15:00",
          "activity": "空港到着・手続き",
          "description": "空港に到着し、チェックイン、セキュリティチェックを済ませ、搭乗ゲートへ向かいます。"
        },
        {
          "time": "17:00",
          "activity": "ニューヨーク出発",
          "description": "ニューヨークを発ち、帰国の途へ。"
        }
      ]
    }
  ],
  "references": [
    {
      "title": "Blog Post",
      "url": "https://travel.tomokichidiary.com/posts/spain7",
      "snippet": "フカレーとハヤシライスの間みたいな感じ、私的には好みドンピシャでとても美味しかったです。\r\nベルギービールは、実は私、ビールがあまり得意ではなく、日本では飲めなかったのですが、せっかくベルギーに来てビールを飲まないのもなと思い、注文してみました。\r\nいくつか種類があり、店員さんにお願いして飲みやすいものにしてもらったのですが、とても飲みやすく、ビールが苦手な私でも美味しく飲むことができました。\r\n..."
    }
  ]
}