{
  "id": "6ecymm9yixq",
  "destination": "ソウル",
  "description": "友人との2泊3日のソウル旅行。K-Beauty、最新ファッション、トレンドグルメ、おしゃれなカフェ巡りを中心に、アクティブにソウルの「今」を満喫するプランです。",
  "heroImage": "https://images.unsplash.com/photo-1622967889059-b5e08a6bfb29?crop=entropy&cs=tinysrgb&fit=max&fm=jpg&ixid=M3w4NTQ4NTd8MHwxfHJhbmRvbXx8fHx8fHx8fDE3Njg0MDI1NDd8&ixlib=rb-4.1.0&q=80&w=1080",
  "heroImagePhotographer": "Soyoung HAN",
  "heroImagePhotographerUrl": "https://unsplash.com/@soflightsto?utm_source=Tabidea&utm_medium=referral",
  "days": [
    {
      "day": 1,
      "title": "K-Beautyと定番ショッピングの聖地巡り",
      "activities": [
        {
          "time": "09:00",
          "activity": "明洞餃子で活力をつける朝食",
          "description": "ソウル到着後、まずは明洞へ。定番の『明洞餃子』で、濃厚なスープのカルグクスとマンドゥ（餃子）を堪能し、アクティブな一日のスタートを切ります。"
        },
        {
          "time": "10:30",
          "activity": "明洞でK-Beautyコスメを徹底購入",
          "description": "明洞のメインストリートで、オリーブヤング本店や各ブランドのフラッグシップストアを巡ります。話題のシートマスクや新作コスメをチェックし、友人とお得なセットを探しながら買い物を楽しみます。"
        },
        {
          "time": "13:00",
          "activity": "南大門市場で市場グルメ（昼食）",
          "description": "活気あふれる南大門市場へ移動。市場内の食堂や屋台で、名物のカルグクス横丁や、熱々の野菜ホットクなど、庶民的な韓国グルメを体験します。"
        },
        {
          "time": "14:30",
          "activity": "南大門市場で定番土産探し",
          "description": "市場内で、韓国海苔、伝統的な食器、アクセサリーなど、定番のお土産を探します。店員さんとの価格交渉も市場の醍醐味です。"
        },
        {
          "time": "17:00",
          "activity": "東大門デザインプラザ（DDP）とファッションモール散策",
          "description": "東大門エリアへ移動。近未来的なDDPの外観を見学し、その後、DOOTA MALLなどの大型ファッションビルで最新のトレンドファッションをチェックします。"
        },
        {
          "time": "19:30",
          "activity": "タッカンマリ横丁で夕食",
          "description": "東大門のタッカンマリ横丁へ。鶏一羽を丸ごと煮込んだタッカンマリを、友人とのシェアグルメとして楽しみます。〆のカルグクスまでしっかり味わい、冷えた体を温めます。"
        },
        {
          "time": "21:00",
          "activity": "東大門ナイトショッピング体験",
          "description": "卸売市場（apm PLACEやミリオレなど）が活気づく時間帯に、夜の東大門を散策。購入は難しくても、ソウルのファッションのエネルギーと熱気を肌で感じます。"
        }
      ]
    },
    {
      "day": 2,
      "title": "トレンドカフェと江南ファッション探訪",
      "activities": [
        {
          "time": "09:00",
          "activity": "延南洞のトレンドカフェでブランチ",
          "description": "若者に人気の延南洞へ。写真映えする内装のカフェを選び、おしゃれなベーグルやトースト、コーヒーでゆったりとブランチを楽しみます。"
        },
        {
          "time": "11:00",
          "activity": "弘大ストリートファッション＆雑貨ショッピング",
          "description": "弘大エリアへ移動。個性的なストリートブランドや、インディーズのデザイナーズショップ、雑貨店を巡り、カジュアルで個性的なアイテムを探します。"
        },
        {
          "time": "13:30",
          "activity": "カロスキルのおしゃれレストランで昼食",
          "description": "江南エリアのカロスキルへ移動。並木道沿いにある洗練された雰囲気のレストランで、モダンコリアンやフュージョン料理を楽しみます。"
        },
        {
          "time": "15:00",
          "activity": "カロスキルでハイセンスなファッション巡り",
          "description": "カロスキルのメインストリートと裏通りを散策。韓国国内外のセレクトショップや、コスメブランドのフラッグシップストアを巡り、洗練されたファッションアイテムをチェックします。"
        },
        {
          "time": "17:30",
          "activity": "狎鴎亭ロデオで高級美容・ファッションリサーチ",
          "description": "狎鴎亭ロデオ通りへ。高級ブランド店や、話題の美容クリニックが集まるエリアをリサーチ。ギャラリア百貨店などで、江南ならではのラグジュアリーな雰囲気を体験します。"
        },
        {
          "time": "19:30",
          "activity": "狎鴎亭/清潭洞で贅沢なディナー",
          "description": "清潭洞エリアの高級感のある焼肉店や、雰囲気の良いフュージョン料理店を選び、旅の思い出を語り合いながら、少し贅沢なディナーを楽しみます。"
        },
        {
          "time": "21:00",
          "activity": "江南エリアのデザートカフェまたはバーで締めくくり",
          "description": "江南駅周辺や狎鴎亭エリアの、夜遅くまで営業しているおしゃれなデザートカフェで、トレンドのスイーツを味わうか、ルーフトップバーで夜景を眺めながら旅の締めくくりをします。"
        }
      ]
    },
    {
      "day": 3,
      "title": "伝統とモダンが交差するエリア散策と帰国",
      "activities": [
        {
          "time": "08:00",
          "activity": "朝食：三清洞のおしゃれなブランチカフェ",
          "description": "最終日の朝食は、三清洞エリアにあるトレンディなベーカリーカフェやブランチ専門店へ。おしゃれな雰囲気の中で、美味しいパンやエッグベネディクトなどをいただき、アクティブな一日のスタートを切ります。"
        },
        {
          "time": "09:00",
          "activity": "北村韓屋村（Bukchon Hanok Village）散策",
          "description": "伝統的な韓屋が密集する北村へ。早朝は観光客が比較的少なく、静かに散策できます。「北村八景」を巡り、ソウルの歴史的な美しさとモダンな街並みが融合する景色を写真に収めます。"
        },
        {
          "time": "11:00",
          "activity": "三清洞（Samcheong-dong）で最後のトレンドショッピングとカフェタイム",
          "description": "北村から三清洞通りへ移動。このエリアは、個性的なブティックやセレクトショップ、コスメショップが並びます。友人との最後のショッピングを楽しみ、トレンドアイテムをチェック。途中で人気のデザートカフェに立ち寄り、おしゃれな空間で休憩します。"
        },
        {
          "time": "13:00",
          "activity": "昼食：仁寺洞（Insadong）で伝統的な韓定食",
          "description": "仁寺洞へ移動し、伝統的な雰囲気のレストランで昼食。最後の韓国グルメとして、様々な小皿料理が並ぶ豪華な韓定食（ハンジョンシク）を堪能します。"
        },
        {
          "time": "14:00",
          "activity": "仁寺洞 伝統文化ストリート散策とお土産探し",
          "description": "仁寺洞のメインストリートを散策。伝統工芸品、美術品、茶器などが並ぶ店を見て回ります。特に、モダンなデザインの工芸品が集まる複合施設「サムジキル（Ssamziegil）」で、友人や自分へのお土産を探します。"
        },
        {
          "time": "15:00",
          "activity": "ホテルへ戻り、空港へ移動開始",
          "description": "ホテルに戻り、預けていた荷物をピックアップ。帰国便の時間に合わせて、空港鉄道（A'REX）などを利用し、仁川国際空港または金浦国際空港へ向かいます。（※フライトの3時間前には空港に到着できるよう逆算して移動を開始します。）"
        },
        {
          "time": "18:00",
          "activity": "夕食：空港で軽食と最後の買い物",
          "description": "出国手続き後、空港内の免税店で買い残したコスメや食品をチェック。搭乗前に空港内のレストランやラウンジで軽めの夕食を取ります。"
        }
      ]
    }
  ],
  "references": [
    {
      "title": "Blog Post",
      "url": "https://travel.tomokichidiary.com/posts/spain7",
      "snippet": "フカレーとハヤシライスの間みたいな感じ、私的には好みドンピシャでとても美味しかったです。\r\nベルギービールは、実は私、ビールがあまり得意ではなく、日本では飲めなかったのですが、せっかくベルギーに来てビールを飲まないのもなと思い、注文してみました。\r\nいくつか種類があり、店員さんにお願いして飲みやすいものにしてもらったのですが、とても飲みやすく、ビールが苦手な私でも美味しく飲むことができました。\r\n..."
    }
  ]
}